sceptre_cloudformation_package_handler.py
sceptre_cloudformation_package_handler-0.1.1.dist-info/LICENSE
sceptre_cloudformation_package_handler-0.1.1.dist-info/METADATA
sceptre_cloudformation_package_handler-0.1.1.dist-info/WHEEL
sceptre_cloudformation_package_handler-0.1.1.dist-info/entry_points.txt
sceptre_cloudformation_package_handler-0.1.1.dist-info/top_level.txt
sceptre_cloudformation_package_handler-0.1.1.dist-info/RECORD
