Metadata-Version: 2.1
Name: sceptre-cloudformation-package-handler
Version: 0.1.1
Summary: A template handler for cloudformation package command.
Home-page: https://github.com/trinopoty/sceptre-cloudformation-package-handler
Author: Trinopoty Biswas
Author-email: Trinopoty Biswas <trinopoty@outlook.com>
Project-URL: Homepage, https://github.com/trinopoty/sceptre-cloudformation-package-handler
Project-URL: Issues, https://github.com/trinopoty/sceptre-cloudformation-package-handler/issues
Classifier: Programming Language :: Python :: 3
Classifier: License :: OSI Approved :: MIT License
Classifier: Operating System :: OS Independent
Requires-Python: >=3.10
License-File: LICENSE
